<package>
  <description brief="hrl_dynamic_mpc">

     hrl_dynamic_mpc

  </description>
  <author>Marc Killpack</author>
  <license>BSD</license>
  <review status="unreviewed" notes=""/>
  <url>http://ros.org/wiki/hrl_dynamic_mpc</url>
  <depend package="rospy"/>
  <depend package="geometry_msgs"/>
  <depend package="hrl_lib"/>
  <depend package="sensor_msgs"/>
  <depend package="kdl"/>
  <depend package="equilibrium_point_control"/>
  <depend package="hrl_haptic_manipulation_in_clutter_msgs"/>
  <depend package="hrl_haptic_manipulation_in_clutter_srvs"/>
  <!--<depend package="m3ctrl_msgs"/>-->
  <depend package="m3skin_ros"/>


</package>


